Workbook

Sheet US_Regional_Sales_Data
A1: OrderNumber | B1: SalesChannel | C1: WarehouseCode | D1: ProcuredDate | E1: OrderDate | F1: ShipDate | G1: DeliveryDate | H1: CurrencyCode | I1: _SalesTeamID | J1: _CustomerID | K1: _StoreID | L1: _ProductID | M1: Order Quantity | N1: Discount Applied | O1: Unit Cost | P1: Unit Price
A2: SO - 000101 | B2: In-Store | C2: WARE-UHY1004 | D2: 43100 | E2: 43251 | F2: 43265 | G2: 43270 | H2: USD | I2: 6 | J2: 15 | K2: 259 | L2: 12 | M2: 5 | N2: 0.075 | O2: 1001.18 | P2: 1963.1
A3: SO - 000102 | B3: Online | C3: WARE-NMK1003 | D3: 43100 | E3: 43251 | F3: 43273 | G3: 43283 | H3: USD | I3: 14 | J3: 20 | K3: 196 | L3: 27 | M3: 3 | N3: 0.075 | O3: 3348.66 | P3: 3939.6
A4: SO - 000103 | B4: Distributor | C4: WARE-UHY1004 | D4: 43100 | E4: 43251 | F4: 43272 | G4: 43282 | H4: USD | I4: 21 | J4: 16 | K4: 213 | L4: 16 | M4: 1 | N4: 0.05 | O4: 781.22 | P4: 1775.5
A5: SO - 000104 | B5: Wholesale | C5: WARE-NMK1003 | D5: 43100 | E5: 43251 | F5: 43253 | G5: 43258 | H5: USD | I5: 28 | J5: 48 | K5: 107 | L5: 23 | M5: 8 | N5: 0.075 | O5: 1464.69 | P5: 2324.9
A6: SO - 000105 | B6: Distributor | C6: WARE-NMK1003 | D6: 43200 | E6: 43251 | F6: 43267 | G6: 43277 | H6: USD | I6: 22 | J6: 49 | K6: 111 | L6: 26 | M6: 8 | N6: 0.1 | O6: 1476.14 | P6: 1822.4
A7: SO - 000106 | B7: Online | C7: WARE-PUJ1005 | D7: 43100 | E7: 43251 | F7: 43259 | G7: 43264 | H7: USD | I7: 12 | J7: 21 | K7: 285 | L7: 1 | M7: 5 | N7: 0.05 | O7: 446.56 | P7: 1038.5
A8: SO - 000107 | B8: In-Store | C8: WARE-XYS1001 | D8: 43100 | E8: 43251 | F8: 43259 | G8: 43265 | H8: USD | I8: 10 | J8: 14 | K8: 6 | L8: 5 | M8: 4 | N8: 0.15 | O8: 536.67 | P8: 1192.6
A9: SO - 000108 | B9: In-Store | C9: WARE-PUJ1005 | D9: 43200 | E9: 43251 | F9: 43277 | G9: 43282 | H9: USD | I9: 6 | J9: 9 | K9: 280 | L9: 46 | M9: 5 | N9: 0.05 | O9: 1525.19 | P9: 1815.7
A10: SO - 000109 | B10: In-Store | C10: WARE-PUJ1005 | D10: 43100 | E10: 43252 | F10: 43267 | G10: 43272 | H10: USD | I10: 4 | J10: 9 | K10: 299 | L10: 47 | M10: 4 | N10: 0.3 | O10: 2211.2 | P10: 3879.3
A11: SO - 000110 | B11: In-Store | C11: WARE-UHY1004 | D11: 43100 | E11: 43252 | F11: 43280 | G11: 43282 | H11: USD | I11: 10 | J11: 33 | K11: 261 | L11: 13 | M11: 8 | N11: 0.05 | O11: 1212.97 | P11: 1956.4
A12: SO - 000111 | B12: Distributor | C12: WARE-XYS1001 | D12: 43100 | E12: 43252 | F12: 43266 | G12: 43271 | H12: USD | I12: 23 | J12: 21 | K12: 17 | L12: 38 | M12: 6 | N12: 0.1 | O12: 124.62 | P12: 201
A13: SO - 000112 | B13: In-Store | C13: WARE-NMK1003 | D13: 43200 | E13: 43252 | F13: 43258 | G13: 43268 | H13: USD | I13: 10 | J13: 21 | K13: 152 | L13: 40 | M13: 5 | N13: 0.15 | O13: 2762.28 | P13: 6277.9
... A7992: SO - 0008091 | B7992: In-Store | C7992: WARE-UHY1004 | D7992: 44100 | E7992: 44195 | F7992: 44209 | G7992: 44215 | H7992: USD | I7992: 6 | J7992: 41 | K7992: 237 | L7992: 43 | M7992: 5 | N7992: 0.075 | O7992: 1370.82 | P7992: 2211

Sheet Financial KPIS
A1: Revenue Per Order | B1: Cost Per Order | C1: Profit per order | D1: Profit margin Per order | E1: Total Revenue (after discounts) | F1: Total Cost | G1: Total Profit | H1: Profit Margin | I1: Revenue lost to discounts
A2: =US_Regional_Sales_Data!P2*US_Regional_Sales_Data!M2*(1-US_Regional_Sales_Data!N2) -> 9079.3375 | B2: =US_Regional_Sales_Data!O2*US_Regional_Sales_Data!M2 -> 5005.9 | C2: =A2-B2 -> 4073.4375 | D2: =C2/A2 -> 0.4486492 | E2: {=SUM(US_Regional_Sales_Data!M2:M7992*US_Regional_Sales_Data!P2:P7992*(1-US_Regional_Sales_Data!N2:N7992))} -> 73143380 | F2: =SUM(B2:B7992) -> 51818069 | G2: =SUM(E2-F2) -> 21325311 | H2: =G2/E2 -> 0.2915549 | I2: {=SUM(US_Regional_Sales_Data!P2:P7992*US_Regional_Sales_Data!M2:M7992*US_Regional_Sales_Data!N2:N7992)} -> 9549346.9
A3: =US_Regional_Sales_Data!P3*US_Regional_Sales_Data!M3*(1-US_Regional_Sales_Data!N3) -> 10932.39 | B3: =US_Regional_Sales_Data!O3*US_Regional_Sales_Data!M3 -> 10045.98 | C3: =A3-B3 -> 886.41 | D3: =C3/A3 -> 0.081081081
A4: =US_Regional_Sales_Data!P4*US_Regional_Sales_Data!M4*(1-US_Regional_Sales_Data!N4) -> 1686.725 | B4: =US_Regional_Sales_Data!O4*US_Regional_Sales_Data!M4 -> 781.22 | C4: =A4-B4 -> 905.505 | D4: =C4/A4 -> 0.53684211
A5: =US_Regional_Sales_Data!P5*US_Regional_Sales_Data!M5*(1-US_Regional_Sales_Data!N5) -> 17204.26 | B5: =US_Regional_Sales_Data!O5*US_Regional_Sales_Data!M5 -> 11717.52 | C5: =A5-B5 -> 5486.74 | D5: =C5/A5 -> 0.31891752
A6: =US_Regional_Sales_Data!P6*US_Regional_Sales_Data!M6*(1-US_Regional_Sales_Data!N6) -> 13121.28 | B6: =US_Regional_Sales_Data!O6*US_Regional_Sales_Data!M6 -> 11809.12 | C6: =A6-B6 -> 1312.16 | D6: =C6/A6 -> 0.10000244
A7: =US_Regional_Sales_Data!P7*US_Regional_Sales_Data!M7*(1-US_Regional_Sales_Data!N7) -> 4932.875 | B7: =US_Regional_Sales_Data!O7*US_Regional_Sales_Data!M7 -> 2232.8 | C7: =A7-B7 -> 2700.075 | D7: =C7/A7 -> 0.54736335
A8: =US_Regional_Sales_Data!P8*US_Regional_Sales_Data!M8*(1-US_Regional_Sales_Data!N8) -> 4054.84 | B8: =US_Regional_Sales_Data!O8*US_Regional_Sales_Data!M8 -> 2146.68 | C8: =A8-B8 -> 1908.16 | D8: =C8/A8 -> 0.47058824
A9: =US_Regional_Sales_Data!P9*US_Regional_Sales_Data!M9*(1-US_Regional_Sales_Data!N9) -> 8624.575 | B9: =US_Regional_Sales_Data!O9*US_Regional_Sales_Data!M9 -> 7625.95 | C9: =A9-B9 -> 998.625 | D9: =C9/A9 -> 0.11578831
A10: =US_Regional_Sales_Data!P10*US_Regional_Sales_Data!M10*(1-US_Regional_Sales_Data!N10) -> 10862.04 | B10: =US_Regional_Sales_Data!O10*US_Regional_Sales_Data!M10 -> 8844.8 | C10: =A10-B10 -> 2017.24 | D10: =C10/A10 -> 0.18571465
A11: =US_Regional_Sales_Data!P11*US_Regional_Sales_Data!M11*(1-US_Regional_Sales_Data!N11) -> 14868.64 | B11: =US_Regional_Sales_Data!O11*US_Regional_Sales_Data!M11 -> 9703.76 | C11: =A11-B11 -> 5164.88 | D11: =C11/A11 -> 0.34736734
A12: =US_Regional_Sales_Data!P12*US_Regional_Sales_Data!M12*(1-US_Regional_Sales_Data!N12) -> 1085.4 | B12: =US_Regional_Sales_Data!O12*US_Regional_Sales_Data!M12 -> 747.72 | C12: =A12-B12 -> 337.68 | D12: =C12/A12 -> 0.31111111
A13: =US_Regional_Sales_Data!P13*US_Regional_Sales_Data!M13*(1-US_Regional_Sales_Data!N13) -> 26681.075 | B13: =US_Regional_Sales_Data!O13*US_Regional_Sales_Data!M13 -> 13811.4 | C13: =A13-B13 -> 12869.675 | D13: =C13/A13 -> 0.48235219
A14: =US_Regional_Sales_Data!P14*US_Regional_Sales_Data!M14*(1-US_Regional_Sales_Data!N14) -> 4996.525 | B14: =US_Regional_Sales_Data!O14*US_Regional_Sales_Data!M14 -> 3208.3 | C14: =A14-B14 -> 1788.225 | D14: =C14/A14 -> 0.35789374
... A7992: =US_Regional_Sales_Data!P7992*US_Regional_Sales_Data!M7992*(1-US_Regional_Sales_Data!N7992) -> 10225.875 | B7992: =US_Regional_Sales_Data!O7992*US_Regional_Sales_Data!M7992 -> 6854.1 | C7992: =A7992-B7992 -> 3371.775 | D7992: =C7992/A7992 -> 0.32972973
